mdslogger/__init__.py
mdslogger/liblogger.py
mdslogger/mdslogger.py
mds_mdslogger-0.5.3.dist-info/METADATA
mds_mdslogger-0.5.3.dist-info/WHEEL
mds_mdslogger-0.5.3.dist-info/top_level.txt
mds_mdslogger-0.5.3.dist-info/RECORD
